<network>
  <map width="128" height="128">
    <start x="64" y="32" />
    <end x="32" y="96" />
    <town x="32" y="96" />
    <town x="32" y="96" />
    <town x="32" y="96" />
  </map>
  <vertex id="0" x="40" y="95" />
  <vertex id="1" x="77" y="16" />
  <vertex id="2" x="64" y="73" />
  <vertex id="3" x="39" y="26" />
  <vertex id="4" x="59" y="80" />
  <vertex id="5" x="3" y="48" />
  <vertex id="6" x="50" y="38" />
  <vertex id="7" x="57" y="77" />
  <vertex id="8" x="27" y="26" />
  <vertex id="9" x="40" y="62" />
  <vertex id="10" x="37" y="80" />
  <vertex id="11" x="71" y="82" />
  <vertex id="12" x="1" y="5" />
  <vertex id="13" x="17" y="82" />
  <vertex id="14" x="49" y="67" />
  <vertex id="15" x="77" y="34" />
  <vertex id="16" x="34" y="59" />
  <vertex id="17" x="76" y="63" />
  <vertex id="18" x="18" y="22" />
  <vertex id="19" x="48" y="62" />
  <vertex id="20" x="78" y="53" />
  <vertex id="21" x="3" y="42" />
  <vertex id="22" x="20" y="69" />
  <vertex id="23" x="63" y="14" />
  <vertex id="24" x="48" y="27" />
  <vertex id="25" x="3" y="78" />
  <vertex id="26" x="7" y="27" />
  <vertex id="27" x="23" y="60" />
  <vertex id="28" x="23" y="94" />
  <vertex id="29" x="15" y="58" />
  <vertex id="30" x="55" y="56" />
  <vertex id="31" x="77" y="92" />
  <vertex id="32" x="3" y="68" />
  <vertex id="33" x="14" y="91" />
  <vertex id="34" x="61" y="93" />
  <vertex id="35" x="58" y="5" />
  <vertex id="36" x="78" y="78" />
  <vertex id="37" x="83" y="84" />
  <vertex id="38" x="76" y="29" />
  <vertex id="39" x="61" y="32" />
  <vertex id="40" x="42" y="2" />
  <vertex id="41" x="34" y="22" />
  <vertex id="42" x="63" y="99" />
  <vertex id="43" x="26" y="6" />
  <vertex id="44" x="35" y="16" />
  <vertex id="45" x="39" y="24" />
  <vertex id="46" x="7" y="89" />
  <vertex id="47" x="6" y="22" />
  <vertex id="48" x="76" y="10" />
  <vertex id="49" x="38" y="52" />
  <vertex id="50" x="54" y="71" />
  <vertex id="51" x="53" y="54" />
  <vertex id="52" x="68" y="98" />
  <vertex id="53" x="99" y="29" />
  <vertex id="54" x="43" y="39" />
  <vertex id="55" x="83" y="94" />
  <vertex id="56" x="32" y="83" />
  <vertex id="57" x="16" y="53" />
  <vertex id="58" x="21" y="54" />
  <vertex id="59" x="29" y="4" />
  <vertex id="60" x="41" y="7" />
  <vertex id="61" x="56" y="44" />
  <vertex id="62" x="54" y="34" />
  <vertex id="63" x="98" y="89" />
  <vertex id="64" x="71" y="61" />
  <vertex id="65" x="7" y="66" />
  <vertex id="66" x="90" y="9" />
  <vertex id="67" x="77" y="70" />
  <vertex id="68" x="49" y="80" />
  <vertex id="69" x="53" y="65" />
  <vertex id="70" x="99" y="97" />
  <vertex id="71" x="62" y="96" />
  <vertex id="72" x="33" y="44" />
  <vertex id="73" x="91" y="23" />
  <vertex id="74" x="72" y="53" />
  <vertex id="75" x="0" y="21" />
  <vertex id="76" x="81" y="34" />
  <vertex id="77" x="11" y="47" />
  <vertex id="78" x="15" y="8" />
  <vertex id="79" x="99" y="34" />
  <vertex id="80" x="0" y="10" />
  <vertex id="81" x="57" y="82" />
  <vertex id="82" x="31" y="17" />
  <vertex id="83" x="4" y="23" />
  <vertex id="84" x="6" y="46" />
  <vertex id="85" x="3" y="41" />
  <vertex id="86" x="0" y="63" />
  <vertex id="87" x="5" y="43" />
  <vertex id="88" x="44" y="59" />
  <vertex id="89" x="11" y="9" />
  <vertex id="90" x="42" y="74" />
  <vertex id="91" x="16" y="18" />
  <vertex id="92" x="60" y="85" />
  <vertex id="93" x="84" y="56" />
  <vertex id="94" x="98" y="30" />
  <vertex id="95" x="54" y="41" />
  <vertex id="96" x="80" y="19" />
  <vertex id="97" x="65" y="89" />
  <vertex id="98" x="39" y="80" />
  <vertex id="99" x="65" y="15" />
  <edge start="40" end="68" />
  <edge start="17" end="26" />
  <edge start="49" end="59" />
  <edge start="20" end="18" />
  <edge start="28" end="67" />
  <edge start="2" end="56" />
  <edge start="96" end="90" />
  <edge start="91" end="25" />
  <edge start="94" end="39" />
  <edge start="21" end="45" />
  <edge start="32" end="48" />
  <edge start="25" end="76" />
  <edge start="92" end="62" />
  <edge start="61" end="81" />
  <edge start="98" end="16" />
  <edge start="4" end="64" />
  <edge start="94" end="95" />
  <edge start="69" end="74" />
  <edge start="56" end="90" />
  <edge start="68" end="1" />
  <edge start="64" end="66" />
  <edge start="27" end="30" />
  <edge start="27" end="97" />
  <edge start="44" end="90" />
  <edge start="27" end="39" />
  <edge start="94" end="99" />
  <edge start="58" end="19" />
  <edge start="83" end="91" />
  <edge start="42" end="41" />
  <edge start="33" end="87" />
  <edge start="97" end="39" />
  <edge start="20" end="12" />
  <edge start="62" end="37" />
  <edge start="62" end="1" />
  <edge start="20" end="17" />
  <edge start="69" end="4" />
  <edge start="71" end="20" />
  <edge start="80" end="66" />
  <edge start="21" end="94" />
  <edge start="48" end="94" />
  <edge start="18" end="71" />
  <edge start="53" end="58" />
  <edge start="21" end="4" />
  <edge start="6" end="74" />
  <edge start="12" end="78" />
  <edge start="31" end="15" />
  <edge start="56" end="81" />
  <edge start="3" end="25" />
  <edge start="46" end="14" />
  <edge start="68" end="89" />
  <edge start="35" end="43" />
  <edge start="70" end="10" />
  <edge start="70" end="90" />
  <edge start="28" end="37" />
  <edge start="38" end="16" />
  <edge start="70" end="48" />
  <edge start="93" end="38" />
  <edge start="68" end="26" />
  <edge start="86" end="61" />
  <edge start="91" end="58" />
  <edge start="31" end="87" />
  <edge start="88" end="41" />
  <edge start="85" end="53" />
  <edge start="47" end="89" />
  <edge start="17" end="55" />
  <edge start="20" end="6" />
  <edge start="26" end="58" />
  <edge start="59" end="75" />
  <edge start="1" end="42" />
  <edge start="87" end="30" />
  <edge start="75" end="68" />
  <edge start="36" end="96" />
  <edge start="7" end="83" />
  <edge start="21" end="17" />
  <edge start="12" end="76" />
  <edge start="39" end="84" />
  <edge start="22" end="9" />
  <edge start="58" end="48" />
  <edge start="55" end="28" />
  <edge start="25" end="16" />
  <edge start="42" end="39" />
  <edge start="20" end="82" />
  <edge start="95" end="63" />
  <edge start="21" end="34" />
  <edge start="79" end="93" />
  <edge start="25" end="43" />
  <edge start="73" end="61" />
  <edge start="82" end="63" />
  <edge start="50" end="91" />
  <edge start="34" end="1" />
  <edge start="31" end="30" />
  <edge start="77" end="40" />
  <edge start="16" end="36" />
  <edge start="84" end="16" />
  <edge start="0" end="10" />
  <edge start="19" end="72" />
  <edge start="17" end="71" />
  <edge start="87" end="36" />
  <edge start="47" end="53" />
  <edge start="0" end="44" />
  <edge start="61" end="87" />
  <edge start="37" end="18" />
  <edge start="50" end="95" />
  <edge start="10" end="61" />
  <edge start="27" end="95" />
  <edge start="97" end="63" />
  <edge start="93" end="23" />
  <edge start="84" end="12" />
  <edge start="61" end="80" />
  <edge start="66" end="59" />
  <edge start="79" end="5" />
  <edge start="34" end="69" />
  <edge start="73" end="52" />
  <edge start="26" end="2" />
  <edge start="73" end="46" />
  <edge start="15" end="97" />
  <edge start="91" end="89" />
  <edge start="39" end="44" />
  <edge start="92" end="59" />
  <edge start="89" end="20" />
  <edge start="25" end="22" />
  <edge start="89" end="4" />
  <edge start="12" end="56" />
  <edge start="79" end="93" />
  <edge start="86" end="74" />
  <edge start="75" end="67" />
  <edge start="87" end="41" />
  <edge start="65" end="56" />
  <edge start="52" end="68" />
  <edge start="44" end="97" />
  <edge start="69" end="7" />
  <edge start="88" end="80" />
  <edge start="80" end="0" />
  <edge start="72" end="4" />
  <edge start="84" end="40" />
  <edge start="19" end="2" />
  <edge start="90" end="45" />
  <edge start="33" end="56" />
  <edge start="15" end="29" />
  <edge start="56" end="17" />
  <edge start="73" end="33" />
  <edge start="16" end="98" />
  <edge start="70" end="47" />
  <edge start="9" end="49" />
  <edge start="24" end="83" />
  <edge start="92" end="24" />
  <edge start="14" end="91" />
  <edge start="51" end="18" />
  <edge start="34" end="8" />
  <edge start="24" end="11" />
  <edge start="84" end="74" />
  <edge start="9" end="46" />
  <edge start="55" end="73" />
  <edge start="76" end="42" />
  <edge start="8" end="8" />
  <edge start="40" end="22" />
  <edge start="11" end="27" />
  <edge start="24" end="35" />
  <edge start="91" end="89" />
  <edge start="10" end="32" />
  <edge start="91" end="22" />
  <edge start="79" end="0" />
  <edge start="47" end="94" />
  <edge start="87" end="99" />
  <edge start="93" end="15" />
  <edge start="22" end="7" />
  <edge start="5" end="45" />
  <edge start="32" end="99" />
  <edge start="24" end="69" />
  <edge start="43" end="97" />
  <edge start="71" end="67" />
  <edge start="41" end="16" />
  <edge start="42" end="69" />
  <edge start="13" end="87" />
  <edge start="67" end="15" />
  <edge start="26" end="44" />
  <edge start="98" end="92" />
  <edge start="20" end="62" />
  <edge start="94" end="8" />
  <edge start="98" end="60" />
  <edge start="85" end="77" />
  <edge start="48" end="93" />
  <edge start="85" end="33" />
  <edge start="17" end="65" />
  <edge start="94" end="24" />
  <edge start="11" end="21" />
  <edge start="46" end="12" />
  <edge start="60" end="23" />
  <edge start="81" end="63" />
  <edge start="57" end="78" />
  <edge start="81" end="99" />
  <edge start="31" end="77" />
  <edge start="88" end="77" />
  <edge start="9" end="12" />
  <edge start="24" end="70" />
  <edge start="4" end="15" />
  <edge start="71" end="82" />
  <edge start="11" end="94" />
  <edge start="18" end="48" />
  <edge start="30" end="9" />
  <edge start="52" end="47" />
  <edge start="92" end="42" />
  <edge start="4" end="5" />
  <edge start="98" end="86" />
  <edge start="32" end="96" />
  <edge start="80" end="31" />
  <edge start="50" end="20" />
  <edge start="79" end="86" />
  <edge start="45" end="70" />
  <edge start="4" end="8" />
  <edge start="24" end="4" />
  <edge start="41" end="24" />
  <edge start="20" end="95" />
  <edge start="49" end="63" />
  <edge start="0" end="66" />
  <edge start="4" end="33" />
  <edge start="33" end="48" />
  <edge start="25" end="33" />
  <edge start="6" end="89" />
  <edge start="73" end="83" />
  <edge start="79" end="22" />
  <edge start="80" end="27" />
  <edge start="89" end="72" />
  <edge start="65" end="51" />
  <edge start="3" end="25" />
  <edge start="48" end="48" />
  <edge start="43" end="22" />
  <edge start="85" end="47" />
  <edge start="6" end="68" />
  <edge start="21" end="8" />
  <edge start="55" end="34" />
  <edge start="85" end="65" />
  <edge start="92" end="47" />
  <edge start="98" end="2" />
  <edge start="94" end="45" />
  <edge start="79" end="56" />
  <edge start="97" end="21" />
  <edge start="28" end="1" />
  <edge start="24" end="13" />
  <edge start="34" end="47" />
  <edge start="30" end="98" />
  <edge start="60" end="74" />
  <edge start="17" end="56" />
  <edge start="89" end="11" />
  <edge start="62" end="78" />
  <edge start="26" end="37" />
  <edge start="67" end="65" />
  <edge start="27" end="44" />
  <edge start="36" end="14" />
  <edge start="35" end="42" />
  <edge start="74" end="62" />
  <edge start="57" end="57" />
  <edge start="45" end="92" />
  <edge start="50" end="21" />
  <edge start="93" end="84" />
  <edge start="23" end="93" />
  <edge start="34" end="73" />
  <edge start="77" end="57" />
  <edge start="74" end="10" />
  <edge start="48" end="35" />
  <edge start="57" end="87" />
  <edge start="39" end="15" />
  <edge start="19" end="42" />
  <edge start="89" end="31" />
  <edge start="94" end="84" />
  <edge start="64" end="9" />
  <edge start="78" end="91" />
  <edge start="73" end="67" />
  <edge start="40" end="2" />
  <edge start="29" end="25" />
  <edge start="5" end="68" />
  <edge start="17" end="78" />
  <edge start="54" end="33" />
  <edge start="3" end="93" />
  <edge start="87" end="70" />
  <edge start="69" end="25" />
  <edge start="66" end="99" />
  <edge start="85" end="87" />
  <edge start="23" end="41" />
  <edge start="38" end="3" />
  <edge start="3" end="18" />
  <edge start="27" end="9" />
  <edge start="20" end="13" />
  <edge start="14" end="42" />
  <edge start="0" end="9" />
  <edge start="16" end="72" />
  <edge start="81" end="23" />
  <edge start="29" end="88" />
  <edge start="69" end="61" />
  <edge start="61" end="85" />
  <edge start="38" end="95" />
  <edge start="44" end="23" />
  <edge start="14" end="38" />
  <edge start="43" end="78" />
  <edge start="6" end="86" />
  <edge start="44" end="98" />
  <edge start="64" end="26" />
  <edge start="21" end="87" />
  <edge start="40" end="7" />
  <edge start="57" end="40" />
  <edge start="18" end="61" />
  <edge start="93" end="78" />
  <edge start="53" end="97" />
  <edge start="44" end="43" />
  <edge start="69" end="96" />
  <edge start="17" end="61" />
  <edge start="80" end="52" />
  <edge start="65" end="7" />
  <edge start="74" end="3" />
  <edge start="95" end="81" />
  <edge start="70" end="36" />
  <edge start="36" end="14" />
  <edge start="65" end="17" />
  <edge start="7" end="55" />
  <edge start="1" end="42" />
  <edge start="48" end="61" />
  <edge start="3" end="20" />
  <edge start="67" end="77" />
  <edge start="2" end="65" />
  <edge start="70" end="16" />
  <edge start="93" end="99" />
  <edge start="9" end="9" />
  <edge start="68" end="82" />
  <edge start="18" end="11" />
  <edge start="61" end="13" />
  <edge start="12" end="36" />
  <edge start="12" end="76" />
  <edge start="69" end="82" />
  <edge start="25" end="78" />
  <edge start="12" end="35" />
  <edge start="90" end="89" />
  <edge start="41" end="27" />
  <edge start="48" end="55" />
  <edge start="58" end="59" />
  <edge start="85" end="87" />
  <edge start="5" end="8" />
  <edge start="33" end="79" />
  <edge start="87" end="70" />
  <edge start="27" end="26" />
  <edge start="45" end="82" />
  <edge start="99" end="95" />
  <edge start="94" end="87" />
  <edge start="29" end="11" />
  <edge start="49" end="27" />
  <edge start="50" end="84" />
  <edge start="52" end="23" />
  <edge start="53" end="34" />
  <edge start="26" end="4" />
  <edge start="58" end="81" />
  <edge start="61" end="12" />
  <edge start="24" end="58" />
  <edge start="26" end="73" />
  <edge start="8" end="3" />
  <edge start="2" end="33" />
  <edge start="88" end="98" />
  <edge start="55" end="98" />
  <edge start="32" end="29" />
  <edge start="36" end="94" />
  <edge start="94" end="54" />
  <edge start="97" end="36" />
  <edge start="6" end="30" />
  <edge start="9" end="0" />
  <edge start="35" end="81" />
  <edge start="55" end="99" />
  <edge start="53" end="83" />
  <edge start="12" end="45" />
  <edge start="64" end="33" />
  <edge start="58" end="41" />
  <edge start="69" end="21" />
  <edge start="78" end="25" />
  <edge start="8" end="16" />
  <edge start="39" end="51" />
  <edge start="29" end="53" />
  <edge start="91" end="23" />
  <edge start="98" end="31" />
  <edge start="9" end="3" />
  <edge start="84" end="24" />
  <edge start="5" end="93" />
  <edge start="48" end="26" />
  <edge start="37" end="27" />
  <edge start="48" end="3" />
  <edge start="79" end="5" />
  <edge start="86" end="9" />
  <edge start="34" end="99" />
  <edge start="71" end="95" />
  <edge start="24" end="73" />
  <edge start="75" end="71" />
  <edge start="28" end="90" />
  <edge start="91" end="57" />
  <edge start="70" end="82" />
  <edge start="89" end="32" />
  <edge start="1" end="21" />
  <edge start="73" end="9" />
  <edge start="60" end="39" />
  <edge start="27" end="64" />
  <edge start="92" end="42" />
  <edge start="83" end="51" />
  <edge start="77" end="4" />
  <edge start="36" end="34" />
  <edge start="65" end="20" />
  <edge start="18" end="92" />
  <edge start="51" end="3" />
  <edge start="6" end="36" />
  <edge start="27" end="13" />
  <edge start="96" end="15" />
  <edge start="2" end="91" />
  <edge start="55" end="54" />
  <edge start="37" end="16" />
  <edge start="2" end="58" />
  <edge start="31" end="76" />
  <edge start="49" end="95" />
  <edge start="71" end="7" />
  <edge start="2" end="82" />
  <edge start="90" end="24" />
  <edge start="93" end="23" />
  <edge start="53" end="57" />
  <edge start="92" end="50" />
  <edge start="63" end="97" />
  <edge start="80" end="98" />
  <edge start="14" end="36" />
  <edge start="81" end="46" />
  <edge start="42" end="11" />
  <edge start="61" end="0" />
  <edge start="86" end="28" />
  <edge start="13" end="61" />
  <edge start="2" end="78" />
  <edge start="2" end="88" />
  <edge start="70" end="23" />
  <edge start="20" end="43" />
  <edge start="0" end="24" />
  <edge start="46" end="2" />
  <edge start="19" end="73" />
  <edge start="61" end="45" />
  <edge start="99" end="5" />
  <edge start="90" end="39" />
  <edge start="35" end="3" />
  <edge start="43" end="94" />
  <edge start="95" end="2" />
  <edge start="52" end="59" />
  <edge start="46" end="2" />
  <edge start="95" end="61" />
  <edge start="11" end="32" />
  <edge start="20" end="75" />
  <edge start="54" end="3" />
  <edge start="79" end="40" />
  <edge start="77" end="36" />
  <edge start="98" end="89" />
  <edge start="90" end="78" />
  <edge start="26" end="69" />
  <edge start="50" end="16" />
  <edge start="1" end="81" />
  <edge start="37" end="73" />
  <edge start="25" end="98" />
  <edge start="34" end="7" />
  <edge start="93" end="68" />
  <edge start="71" end="60" />
  <edge start="97" end="98" />
  <edge start="29" end="85" />
  <edge start="91" end="87" />
  <edge start="52" end="86" />
  <edge start="90" end="95" />
  <edge start="25" end="50" />
  <edge start="62" end="98" />
  <edge start="5" end="53" />
  <edge start="4" end="16" />
  <edge start="75" end="82" />
  <edge start="9" end="29" />
  <edge start="0" end="13" />
  <edge start="23" end="38" />
  <edge start="7" end="22" />
  <edge start="40" end="47" />
  <edge start="9" end="11" />
  <edge start="69" end="16" />
  <edge start="39" end="0" />
  <edge start="60" end="5" />
  <edge start="87" end="39" />
  <edge start="17" end="63" />
  <edge start="25" end="6" />
  <edge start="55" end="87" />
  <edge start="10" end="26" />
  <edge start="92" end="80" />
  <edge start="3" end="77" />
  <edge start="92" end="88" />
  <edge start="51" end="67" />
  <edge start="97" end="15" />
  <edge start="61" end="53" />
  <edge start="79" end="30" />
  <edge start="45" end="43" />
  <edge start="86" end="14" />
  <edge start="81" end="46" />
  <edge start="59" end="5" />
  <edge start="93" end="98" />
  <edge start="28" end="36" />
  <edge start="64" end="45" />
  <edge start="4" end="94" />
  <edge start="58" end="36" />
  <edge start="27" end="81" />
  <edge start="29" end="60" />
  <edge start="44" end="32" />
  <edge start="19" end="80" />
  <edge start="64" end="71" />
  <edge start="2" end="44" />
  <edge start="44" end="34" />
  <edge start="59" end="87" />
  <edge start="18" end="82" />
  <edge start="20" end="41" />
  <edge start="5" end="64" />
  <edge start="66" end="87" />
  <edge start="87" end="4" />
  <edge start="48" end="56" />
  <edge start="23" end="5" />
  <edge start="63" end="3" />
  <edge start="57" end="25" />
  <edge start="25" end="98" />
  <edge start="1" end="85" />
  <edge start="99" end="53" />
  <edge start="94" end="1" />
  <edge start="81" end="87" />
  <edge start="3" end="49" />
  <edge start="54" end="94" />
  <edge start="76" end="77" />
  <edge start="27" end="21" />
  <edge start="74" end="16" />
  <edge start="30" end="63" />
  <edge start="14" end="41" />
  <edge start="73" end="39" />
  <edge start="83" end="63" />
  <edge start="56" end="59" />
  <edge start="8" end="98" />
  <edge start="86" end="18" />
  <edge start="8" end="61" />
  <edge start="86" end="32" />
  <edge start="83" end="66" />
  <edge start="46" end="3" />
  <edge start="82" end="79" />
  <edge start="83" end="37" />
  <edge start="50" end="54" />
  <edge start="79" end="46" />
  <edge start="77" end="41" />
  <edge start="29" end="41" />
  <edge start="94" end="62" />
  <edge start="83" end="59" />
  <edge start="12" end="59" />
  <edge start="70" end="31" />
  <edge start="45" end="22" />
  <edge start="78" end="4" />
  <edge start="63" end="35" />
  <edge start="85" end="14" />
  <edge start="91" end="94" />
  <edge start="38" end="7" />
  <edge start="69" end="26" />
  <edge start="81" end="35" />
  <edge start="57" end="35" />
  <edge start="89" end="29" />
  <edge start="83" end="9" />
  <edge start="81" end="67" />
  <edge start="68" end="45" />
  <edge start="24" end="46" />
  <edge start="77" end="26" />
  <edge start="20" end="23" />
  <edge start="95" end="15" />
  <edge start="58" end="60" />
  <edge start="0" end="79" />
  <edge start="74" end="14" />
  <edge start="68" end="64" />
  <edge start="54" end="82" />
  <edge start="3" end="21" />
  <edge start="71" end="67" />
  <edge start="81" end="48" />
  <edge start="1" end="77" />
  <edge start="70" end="41" />
  <edge start="47" end="35" />
  <edge start="40" end="11" />
  <edge start="35" end="17" />
  <edge start="11" end="39" />
  <edge start="37" end="64" />
  <edge start="74" end="14" />
  <edge start="12" end="54" />
  <edge start="68" end="20" />
  <edge start="35" end="78" />
  <edge start="60" end="75" />
  <edge start="60" end="18" />
  <edge start="54" end="98" />
  <edge start="63" end="47" />
  <edge start="73" end="57" />
  <edge start="65" end="29" />
  <edge start="25" end="43" />
  <edge start="53" end="54" />
  <edge start="67" end="23" />
  <edge start="19" end="88" />
  <edge start="43" end="56" />
  <edge start="3" end="28" />
  <edge start="27" end="90" />
  <edge start="8" end="89" />
  <edge start="9" end="17" />
  <edge start="99" end="60" />
  <edge start="12" end="22" />
  <edge start="16" end="94" />
  <edge start="80" end="29" />
  <edge start="80" end="41" />
  <edge start="47" end="88" />
  <edge start="44" end="54" />
  <edge start="74" end="7" />
  <edge start="39" end="31" />
  <edge start="60" end="58" />
  <edge start="86" end="45" />
  <edge start="1" end="46" />
  <edge start="35" end="4" />
  <edge start="72" end="32" />
  <edge start="91" end="64" />
  <edge start="90" end="74" />
  <edge start="37" end="55" />
  <edge start="58" end="4" />
  <edge start="16" end="2" />
  <edge start="27" end="58" />
  <edge start="73" end="38" />
  <edge start="42" end="78" />
  <edge start="40" end="54" />
  <edge start="12" end="48" />
  <edge start="54" end="19" />
  <edge start="51" end="76" />
  <edge start="28" end="51" />
  <edge start="31" end="53" />
  <edge start="59" end="66" />
  <edge start="87" end="11" />
  <edge start="22" end="47" />
  <edge start="37" end="16" />
  <edge start="50" end="73" />
  <edge start="50" end="88" />
  <edge start="96" end="69" />
  <edge start="91" end="36" />
  <edge start="4" end="1" />
  <edge start="84" end="47" />
  <edge start="2" end="22" />
  <edge start="6" end="80" />
  <edge start="92" end="23" />
  <edge start="78" end="71" />
  <edge start="12" end="14" />
  <edge start="45" end="86" />
  <edge start="24" end="4" />
  <edge start="45" end="50" />
  <edge start="14" end="15" />
  <edge start="36" end="26" />
  <edge start="0" end="26" />
  <edge start="27" end="67" />
  <edge start="4" end="23" />
  <edge start="52" end="84" />
  <edge start="28" end="14" />
  <edge start="72" end="27" />
  <edge start="67" end="83" />
  <edge start="50" end="36" />
  <edge start="59" end="7" />
  <edge start="19" end="99" />
  <edge start="69" end="66" />
  <edge start="3" end="36" />
  <edge start="27" end="64" />
  <edge start="63" end="91" />
  <edge start="24" end="40" />
  <edge start="22" end="88" />
  <edge start="65" end="58" />
  <edge start="46" end="76" />
  <edge start="95" end="39" />
  <edge start="75" end="68" />
  <edge start="70" end="94" />
  <edge start="43" end="97" />
  <edge start="41" end="18" />
  <edge start="19" end="40" />
  <edge start="53" end="9" />
  <edge start="90" end="6" />
  <edge start="96" end="36" />
  <edge start="56" end="34" />
  <edge start="22" end="90" />
  <edge start="39" end="39" />
  <edge start="60" end="61" />
  <edge start="59" end="87" />
  <edge start="92" end="83" />
  <edge start="61" end="9" />
  <edge start="37" end="73" />
  <edge start="40" end="20" />
  <edge start="31" end="50" />
  <edge start="29" end="75" />
  <edge start="22" end="5" />
  <edge start="95" end="9" />
  <edge start="45" end="22" />
  <edge start="38" end="15" />
  <edge start="49" end="15" />
  <edge start="92" end="28" />
  <edge start="1" end="11" />
  <edge start="54" end="5" />
  <edge start="99" end="36" />
  <edge start="8" end="9" />
  <edge start="34" end="55" />
  <edge start="5" end="57" />
  <edge start="56" end="9" />
  <edge start="3" end="79" />
  <edge start="68" end="69" />
  <edge start="74" end="45" />
  <edge start="7" end="81" />
  <edge start="12" end="16" />
  <edge start="95" end="29" />
  <edge start="94" end="37" />
  <edge start="22" end="44" />
  <edge start="38" end="77" />
  <edge start="91" end="32" />
  <edge start="7" end="25" />
  <edge start="19" end="35" />
  <edge start="21" end="95" />
  <edge start="42" end="20" />
  <edge start="41" end="67" />
  <edge start="0" end="37" />
  <edge start="53" end="35" />
  <edge start="18" end="59" />
  <edge start="46" end="80" />
  <edge start="40" end="47" />
  <edge start="21" end="20" />
  <edge start="99" end="37" />
  <edge start="9" end="70" />
  <edge start="41" end="71" />
  <edge start="86" end="89" />
  <edge start="17" end="27" />
  <edge start="66" end="23" />
  <edge start="1" end="78" />
  <edge start="59" end="32" />
  <edge start="48" end="79" />
  <edge start="2" end="87" />
  <edge start="40" end="44" />
  <edge start="16" end="58" />
  <edge start="76" end="58" />
  <edge start="18" end="63" />
  <edge start="97" end="57" />
  <edge start="36" end="44" />
  <edge start="10" end="87" />
  <edge start="25" end="82" />
  <edge start="26" end="50" />
  <edge start="53" end="71" />
  <edge start="33" end="51" />
  <edge start="49" end="72" />
  <edge start="71" end="29" />
  <edge start="33" end="40" />
  <edge start="99" end="14" />
  <edge start="31" end="61" />
  <edge start="44" end="34" />
  <edge start="80" end="54" />
  <edge start="20" end="51" />
  <edge start="93" end="82" />
  <edge start="52" end="23" />
  <edge start="91" end="59" />
  <edge start="90" end="21" />
  <edge start="12" end="14" />
  <edge start="52" end="77" />
  <edge start="6" end="97" />
  <edge start="25" end="31" />
  <edge start="53" end="88" />
  <edge start="94" end="43" />
  <edge start="87" end="47" />
  <edge start="25" end="78" />
  <edge start="64" end="83" />
  <edge start="26" end="75" />
  <edge start="99" end="76" />
  <edge start="7" end="70" />
  <edge start="61" end="74" />
  <edge start="57" end="70" />
  <edge start="18" end="10" />
  <edge start="60" end="90" />
  <edge start="81" end="49" />
  <edge start="16" end="19" />
  <edge start="87" end="21" />
  <edge start="7" end="33" />
  <edge start="35" end="13" />
  <edge start="80" end="91" />
  <edge start="59" end="76" />
  <edge start="64" end="46" />
  <edge start="57" end="74" />
  <edge start="58" end="7" />
  <edge start="32" end="15" />
  <edge start="21" end="36" />
  <edge start="6" end="82" />
  <edge start="16" end="31" />
  <edge start="40" end="54" />
  <edge start="12" end="43" />
  <edge start="27" end="4" />
  <edge start="62" end="37" />
  <edge start="30" end="6" />
  <edge start="90" end="43" />
  <edge start="75" end="92" />
  <edge start="39" end="86" />
  <edge start="95" end="15" />
  <edge start="11" end="84" />
  <edge start="10" end="10" />
  <edge start="13" end="43" />
  <edge start="51" end="52" />
  <edge start="57" end="66" />
  <edge start="27" end="80" />
  <edge start="12" end="5" />
  <edge start="4" end="76" />
  <edge start="93" end="81" />
  <edge start="0" end="37" />
  <edge start="64" end="55" />
  <edge start="14" end="26" />
  <edge start="15" end="51" />
  <edge start="83" end="15" />
  <edge start="32" end="40" />
  <edge start="75" end="35" />
  <edge start="41" end="91" />
  <edge start="70" end="31" />
  <edge start="20" end="29" />
  <edge start="41" end="68" />
  <edge start="92" end="75" />
  <edge start="46" end="95" />
  <edge start="10" end="50" />
  <edge start="93" end="85" />
  <edge start="38" end="98" />
  <edge start="99" end="58" />
  <edge start="86" end="58" />
  <edge start="51" end="55" />
  <edge start="69" end="84" />
  <edge start="95" end="62" />
  <edge start="59" end="35" />
  <edge start="20" end="17" />
  <edge start="91" end="92" />
  <edge start="38" end="21" />
  <edge start="34" end="72" />
  <edge start="55" end="63" />
  <edge start="39" end="31" />
  <edge start="45" end="88" />
  <edge start="9" end="19" />
  <edge start="16" end="64" />
  <edge start="57" end="98" />
  <edge start="77" end="33" />
  <edge start="40" end="16" />
  <edge start="48" end="82" />
  <edge start="39" end="15" />
  <edge start="62" end="36" />
  <edge start="34" end="79" />
  <edge start="8" end="56" />
  <edge start="55" end="28" />
  <edge start="4" end="17" />
  <edge start="11" end="72" />
  <edge start="51" end="65" />
  <edge start="43" end="35" />
  <edge start="19" end="54" />
  <edge start="12" end="62" />
  <edge start="46" end="50" />
  <edge start="67" end="30" />
  <edge start="5" end="61" />
  <edge start="58" end="86" />
  <edge start="76" end="74" />
  <edge start="43" end="55" />
  <edge start="81" end="19" />
  <edge start="10" end="19" />
  <edge start="28" end="60" />
  <edge start="22" end="89" />
  <edge start="33" end="80" />
  <edge start="14" end="98" />
  <edge start="53" end="84" />
  <edge start="47" end="12" />
  <edge start="90" end="4" />
  <edge start="97" end="94" />
  <edge start="70" end="77" />
  <edge start="68" end="11" />
  <edge start="68" end="4" />
  <edge start="73" end="47" />
  <edge start="97" end="68" />
  <edge start="52" end="30" />
  <edge start="74" end="55" />
  <edge start="91" end="31" />
  <edge start="54" end="23" />
  <edge start="7" end="58" />
  <edge start="31" end="23" />
  <edge start="29" end="66" />
  <edge start="35" end="69" />
  <edge start="77" end="20" />
  <edge start="14" end="46" />
  <edge start="96" end="72" />
  <edge start="76" end="49" />
  <edge start="85" end="3" />
  <edge start="50" end="98" />
  <edge start="50" end="24" />
  <edge start="86" end="75" />
  <edge start="91" end="64" />
  <edge start="28" end="84" />
  <edge start="24" end="97" />
  <edge start="92" end="15" />
  <edge start="57" end="66" />
  <edge start="97" end="39" />
  <edge start="62" end="46" />
  <edge start="48" end="2" />
  <edge start="76" end="99" />
  <edge start="27" end="53" />
  <edge start="33" end="51" />
  <edge start="72" end="79" />
  <edge start="53" end="25" />
  <edge start="69" end="88" />
  <edge start="81" end="55" />
  <edge start="73" end="82" />
  <edge start="71" end="55" />
  <edge start="32" end="64" />
  <edge start="38" end="51" />
  <edge start="44" end="79" />
  <edge start="28" end="98" />
  <edge start="88" end="29" />
  <edge start="74" end="37" />
  <edge start="86" end="39" />
  <edge start="55" end="48" />
  <edge start="22" end="50" />
  <edge start="96" end="33" />
  <edge start="42" end="40" />
  <edge start="92" end="48" />
  <edge start="30" end="99" />
  <edge start="27" end="4" />
  <edge start="33" end="1" />
  <edge start="93" end="15" />
  <edge start="67" end="7" />
  <edge start="14" end="83" />
  <edge start="63" end="25" />
  <edge start="55" end="47" />
  <edge start="24" end="34" />
  <edge start="62" end="42" />
  <edge start="5" end="16" />
  <edge start="38" end="30" />
  <edge start="32" end="33" />
  <edge start="33" end="23" />
  <edge start="85" end="37" />
  <edge start="13" end="91" />
  <edge start="72" end="90" />
  <edge start="20" end="45" />
  <edge start="52" end="24" />
  <edge start="64" end="86" />
  <edge start="36" end="59" />
  <edge start="69" end="79" />
  <edge start="25" end="71" />
  <edge start="84" end="97" />
  <edge start="95" end="49" />
  <edge start="9" end="8" />
  <edge start="77" end="49" />
  <edge start="42" end="14" />
  <edge start="60" end="97" />
  <edge start="71" end="0" />
  <edge start="68" end="70" />
  <edge start="29" end="29" />
  <edge start="93" end="22" />
  <edge start="11" end="73" />
  <edge start="5" end="9" />
  <edge start="95" end="0" />
  <edge start="69" end="75" />
  <edge start="6" end="46" />
  <edge start="46" end="59" />
  <edge start="5" end="61" />
  <edge start="48" end="36" />
  <edge start="27" end="36" />
  <edge start="28" end="5" />
  <edge start="13" end="23" />
  <edge start="47" end="5" />
  <edge start="85" end="55" />
  <edge start="52" end="64" />
  <edge start="18" end="66" />
  <edge start="29" end="40" />
  <edge start="85" end="2" />
  <edge start="60" end="11" />
  <edge start="92" end="85" />
  <edge start="53" end="8" />
  <edge start="38" end="2" />
  <edge start="42" end="95" />
  <edge start="68" end="0" />
  <edge start="91" end="10" />
  <edge start="52" end="32" />
  <edge start="42" end="92" />
  <edge start="1" end="88" />
  <edge start="9" end="87" />
  <edge start="25" end="99" />
  <edge start="24" end="40" />
  <edge start="47" end="5" />
  <edge start="57" end="40" />
  <edge start="16" end="6" />
  <edge start="73" end="3" />
  <edge start="0" end="37" />
  <edge start="44" end="41" />
  <edge start="83" end="19" />
  <edge start="66" end="11" />
  <edge start="80" end="51" />
  <edge start="37" end="84" />
  <edge start="63" end="42" />
  <edge start="12" end="85" />
  <edge start="23" end="37" />
  <edge start="38" end="96" />
  <edge start="93" end="72" />
  <edge start="85" end="92" />
  <edge start="61" end="13" />
  <edge start="60" end="33" />
  <edge start="44" end="2" />
  <edge start="79" end="61" />
  <edge start="27" end="88" />
  <edge start="10" end="14" />
  <edge start="88" end="0" />
  <edge start="9" end="81" />
  <edge start="22" end="97" />
  <edge start="7" end="73" />
  <edge start="62" end="39" />
  <edge start="77" end="5" />
  <edge start="93" end="72" />
</network>